AUTHORS.rst
CONTRIBUTING.rst
HISTORY.rst
LICENSE
MANIFEST.in
README.rst
setup.py
pyray/__init__.py
pyray/base.py
pyray/client.py
pyray/exceptions.py
pyray/nodes.py
pyray/pools.py
pyray.egg-info/PKG-INFO
pyray.egg-info/SOURCES.txt
pyray.egg-info/dependency_links.txt
pyray.egg-info/not-zip-safe
pyray.egg-info/top_level.txt