Metadata-Version: 1.1
Name: pyray
Version: 0.1.0
Summary: A python client to interact with the Riverbed Stingray REST API.
Home-page: https://github.com/intr1nsic/pyray
Author: Matt Welch
Author-email: mwelch@tallshorts.com
License: BSD
Keywords: pyray
Platform: UNKNOWN
Classifier: Development Status :: 2 - Pre-Alpha
Classifier: Intended Audience :: Developers
Classifier: License :: OSI Approved :: BSD License
Classifier: Natural Language :: English
Classifier: Programming Language :: Python :: 2
Classifier: Programming Language :: Python :: 2.6
Classifier: Programming Language :: Python :: 2.7
Classifier: Programming Language :: Python :: 3
Classifier: Programming Language :: Python :: 3.3
